{"data_data_10140.md":"Wv0jAQ3H","beta_1_characters_065_shastasaurus.md":"Dz2Ubqh9","data_data_10280.md":"_DzCKxuo","beta_1_characters_160_clarent.md":"Hr-Ytp_y","data_data_20230.md":"t6eGpOeR","beta_1_characters_161_zeus.md":"AlTOTKyl","data_data_10200.md":"Qg2QKYNi","data_data_20050.md":"ZsQJu8lh","data_data_20210.md":"u7haItIq","data_data_30360.md":"0LqEm6zS","data_data_10050.md":"uxow52L8","data_data_10230.md":"7CuKxZ-6","data_data_10160.md":"WFdEXIfa","data_data_30030.md":"t1vFFrM8","beta_1_characters_113_collapsar.md":"KrfH5T1g","data_data_30240.md":"ecdipiV_","data_data_10070.md":"VamCHygY","data_data_10110.md":"TYiRc2Vo","beta_1_skins.md":"03k774l6","data_data_30431.md":"80xt9l1O","data_data_40160.md":"KDJ6BtRk","data_data_40250.md":"IaQ97Yg1","data_data_40100.md":"S1f2K9SW","data_data_40240.md":"ShQDzrfi","beta_1_characters_169_ares.md":"jt8-tmKq","data_data_40060.md":"xBQzskcC","data_data_30130.md":"wZMsjYYv","data_data_30040.md":"4zMUGkv1","data_data_50130.md":"qsafGySY","data_data_60210.md":"XPx4_Sb_","data_data_50050.md":"M06E-tVV","data_data_10080.md":"rrP6-TlP","data_data_90321.md":"Qq8BMs3P","beta_1_characters_137_orchid.md":"oakcs_bq","data_data_60191.md":"ihIvwa0E","data_data_40130.md":"sZRn30fw","data_data_40150.md":"j95WR19B","data_data_40030.md":"jGfVOmJX","data_data_30270.md":"A84akT8M","data_data_90351.md":"PaIRebK6","data_data_40180.md":"6h2WlgJP","data_data_10010.md":"cYttG5ub","data_data_40170.md":"Vyr-hRhR","data_data_90030.md":"smTPQCbS","data_data_90060.md":"h_D3EbWN","data_data_30420.md":"i4biV3oA","data_data_60260.md":"QO53vIlv","data_data_86260.md":"txitYvr7","data_data_86250.md":"DHvgg0cw","data_data_30190.md":"IJLansjc","data_data_86280.md":"gNkoPdNd","data_data_90450.md":"wW33dCmo","data_data_90480.md":"6KZZIaXv","data_data_30170.md":"DGrrPWYC","beta_1_characters_167_athena.md":"jNQCl-N9","data_data_80030.md":"Cki60GvD","data_data_20030.md":"yVMdUSw6","data_data_90341.md":"8ldQc2y7","data_data_50260.md":"9qqXhx_C","data_data_80180.md":"b9uNK98w","data_data_30290.md":"CYuETZGI","data_data_30140.md":"ICjpXmNf","data_data_30090.md":"VL782TnO","data_data_10060.md":"xUeImdKa","data_data_50270.md":"G6LPp6F_","data_data_10270.md":"G1jRbjLf","data_data_20160.md":"aMvBOaww","data_data_10170.md":"AnDf4upl","data_data_86130.md":"baNlpoQE","beta_1_characters_021_citrine.md":"ND95wRtL","data_data_10130.md":"qCgcTPnr","data_data_10220.md":"R3eclohy","data_data_30280.md":"uef-UOu5","data_data_20130.md":"ehXIHg5b","data_data_30330.md":"TPiFKSc2","data_data_30300.md":"aOLT81Ng","data_data_70070.md":"94Py6DFq","data_data_10180.md":"RASCYcwd","data_data_40080.md":"XQV9rK5f","data_data_85010.md":"FzuXh8xO","data_data_70270.md":"Aeo2fcAj","data_data_30310.md":"L5_-6oMK","data_data_20060.md":"AmWfgvOP","data_data_40260.md":"vaAv9Wfp","data_data_70330.md":"w8pDJGJf","data_data_20020.md":"7Opd4Acc","data_data_70320.md":"a69vr1Of","data_data_40120.md":"HiuKKYbM","data_data_80050.md":"EIco21Hn","data_data_50220.md":"z0OUr6mX","data_data_90220.md":"_-9Buhdt","data_data_40300.md":"b_8-FFPq","data_data_30180.md":"RtnxklZ8","data_data_86190.md":"Unet3Tke","data_data_50041.md":"7YcZVdme","data_data_90550.md":"N7REgjHi","data_data_80230.md":"t5a0gaFG","data_data_60020.md":"YrxnWnV9","data_data_90350.md":"TI8-kPyC","data_data_80250.md":"p4QeGdI1","data_data_90330.md":"mVWlJ3Y2","data_data_80130.md":"K-isAsZD","data_data_80100.md":"HDGed9c8","data_data_80170.md":"Z7QzE5KO","data_data_50030.md":"10TUCm_m","data_data_60180.md":"NwVQE43Y","data_data_86230.md":"fL4xd-TL","data_data_60140.md":"Op3bAyXd","data_data_30110.md":"ZUDFyfnO","data_data_30050.md":"IOQbYWOG","data_data_50100.md":"M_nhQjhN","data_data_90570.md":"y2cB-xhX","data_data_81010.md":"JclPvZzG","library_files_index_illvstration.md":"g_Ry6nhn","data_data_90150.md":"Wkcs54S8","beta_1_characters_043_fantasia.md":"f3jKwJsm","data_data_93291.md":"d1FCy2XI","data_data_99190.md":"eLeHxWK-","data_data_90190.md":"Toe4BDTL","data_data_40400.md":"IvTgFaHC","data_data_70360.md":"-60xI91b","data_data_90500.md":"RWdFGH5C","data_data_86240.md":"o4Eg9u_7","data_data_60040.md":"BWYBIBjn","data_data_99200.md":"CMT1rzcn","data_data_99220.md":"uycfkBrR","data_data_99320.md":"323UX4rJ","data_data_99070.md":"mIJ_du4b","data_data_99330.md":"gpwQrem0","data_data_99362.md":"07pLuxzd","data_data_99100.md":"EsVavAgT","data_data_70050.md":"rhM-h0S1","data_data_80190.md":"vSN-Ozso","data_data_10030.md":"CMlvOyVA","data_data_86030.md":"m6rBbjqB","data_data_86170.md":"aIv8-4Z9","data_data_20010.md":"AbHcHBQO","data_data_90440.md":"sM_FLHun","data_data_20200.md":"ByYxKMQ3","data_data_86140.md":"q4-CD7Gf","data_data_90650.md":"Y4xwU9EQ","data_data_20070.md":"jw4urZTw","data_data_50280.md":"e21OuANV","data_data_90620.md":"WjnqLYDx","data_data_99180.md":"BIBCabHS","library_files_index_enemies.md":"6kI8OkxM","data_data_99300.md":"4tHnsc01","data_data_99210.md":"-wniWird","data_data_90800.md":"gUe9sz1N","data_data_90460.md":"Hcxvkso9","data_data_90290.md":"V-6-vgGs","data_data_20040.md":"5uknQGed","data_data_30120.md":"2YYcfmcj","data_data_60240.md":"TXHYq8UA","data_data_40040.md":"hDNKqR-Z","data_data_80260.md":"mOcYZXvL","data_data_70100.md":"-FoPBpPB","data_data_10000.md":"1YUKtpp6","data_data_50150.md":"eNyj7ny6","data_data_90020.md":"q-ams0QJ","data_data_99030.md":"MuOLm96d","data_data_86150.md":"17yamO56","data_data_90311.md":"uqsYQPz5","data_data_99240.md":"HthdVjKX","data_data_90361.md":"QXFap-xW","data_data_98011.md":"fGtd8Sft","data_data_60160.md":"wj4gRPxJ","data_data_90540.md":"NIQdZv3t","data_data_86010.md":"lsWmpRZu","data_data_10260.md":"g9RLBKRb","data_data_50090.md":"PUtyZceN","data_data_80140.md":"JP2dKQQb","data_data_93290.md":"yr9f0fEZ","data_data_90250.md":"zacGVQDQ","data_data_40340.md":"rHqt995G","data_data_99363.md":"kOAa8Rf-","data_data_70240.md":"2BD1UTbm","data_data_30060.md":"zY7YaU3A","data_data_50170.md":"Q_dBougw","data_data_86180.md":"HNSoROFA","data_data_30011.md":"DP8yLqkq","data_data_30200.md":"wP3rQRtN","data_data_70200.md":"TS_V9B1H","data_data_50160.md":"G9cuJ6o5","data_data_70120.md":"Fr-pDEvY","data_data_80090.md":"uGdYOTRI","data_data_20140.md":"nYQXWqK1","data_data_71010.md":"gLSRvH4x","data_data_80110.md":"661lqjJR","data_data_50300.md":"GYtYqbb0","data_data_30230.md":"zyqpExMM","data_data_86200.md":"5osZJ3bk","data_data_70090.md":"OtqFBNIf","data_data_70140.md":"2hSVsk8w","data_data_30010.md":"2N0f4Cgj","data_data_90310.md":"kzfSnT_F","data_data_20170.md":"4FEoA8_f","data_data_90270.md":"rYtM61Ug","data_data_40330.md":"67k3KLvT","data_data_86020.md":"x4RZ5FF2","data_data_40280.md":"HThv4W2Y","data_data_90530.md":"aVClNQYU","data_data_30070.md":"s8ZveF9E","data_data_90790.md":"fsfZkWDG","data_data_50250.md":"JTSLMfyA","data_data_90940.md":"PIjplINZ","data_data_86050.md":"rCneTBAu","data_data_99361.md":"Yx-VJ8wx","data_data_99290.md":"SzkmcYZo","data_data_99020.md":"ZiMFTd-C","data_data_93260.md":"fuWu0qfF","data_data_10120.md":"8DgbS8rz","data_data_93270.md":"SSQ7FtXa","data_data_60110.md":"XgGer4fC","data_data_90100.md":"OhHWHPbc","data_data_92110.md":"96SfZid9","data_data_30250.md":"JblTkJHc","data_data_40310.md":"vhh4E8Fd","data_data_90520.md":"Cf0ugte4","data_data_60150.md":"TMSorsrY","data_data_99270.md":"Umv_BcDD","data_data_90080.md":"6CDGZUHW","data_data_30210.md":"r_kEba4n","data_data_90850.md":"ozr6K_MT","data_data_70350.md":"h_PY7vuy","data_data_90851.md":"9ZQoRpnf","data_data_92050.md":"yZxEGG1m","data_data_99381.md":"U_1qEZ-V","data_data_70030.md":"xVFZK3Y0","data_data_99010.md":"YCfB-OOx","data_data_90420.md":"ikUwXsEA","data_data_60220.md":"Rkx60jAq","data_npc.md":"SokOcgwU","data_data_90841.md":"mmGwWzL2","data_data_90010.md":"MrrQajdB","data_data_90881.md":"iRHl9CRa","data_data_70020.md":"URVFG82N","data_data_60050.md":"8karkPlk","data_data_90200.md":"54mjaXWC","data_data_90560.md":"51Dd-vKA","data_data_30020.md":"OvALj2v7","data_data_86070.md":"pAA346m9","data_data_10240.md":"LJVNrcQY","beta_1_characters_105_crimsonfog.md":"1iGbdg_O","data_data_99090.md":"MZqzHOWn","data_data_91020.md":"Y8V1wFak","data_data_30080.md":"wZc17WXi","data_data_90170.md":"weZhIb13","data_data_70260.md":"-jaWJkAM","data_data_93230.md":"xCrAP6F4","data_data_93150.md":"qMe860Ao","data_data_80010.md":"TazrHnfg","data_data_80150.md":"20w6FKey","data_data_90401.md":"2DQd2GhU","beta_1_index.md":"ZwCZgA_g","data_data_90040.md":"8hoBV5Go","data_data_40050.md":"pwRBu5z5","data_kishins.md":"Plmzdz7b","data_data_99250.md":"vag6jPiR","data_data_90180.md":"iAgJtyPs","data_data_90900.md":"XbGDRgJp","data_data_92070.md":"M6ijRV0P","data_data_80220.md":"kOjzq1IV","data_data_90370.md":"LA42vgN4","data_data_90390.md":"w5QP7Ygs","data_data_60010.md":"IPTgYXJh","data_data_40020.md":"K4q-S_yQ","data_data_30400.md":"yQCiMPUa","data_data_50190.md":"1-wIcjW6","data_data_90760.md":"5zXj3l3Q","data_data_90990.md":"Z8_hmjyZ","data_data_93250.md":"TJgjIVNR","data_data_90670.md":"aYDyNtVr","data_data_40290.md":"Zs5w9-Ky","data_data_90331.md":"KFyeuVXW","data_data_91010.md":"o8gpsT_K","data_data_90870.md":"PIvgP-rJ","data_data_93130.md":"DOM-IZDI","data_data_99310.md":"yTpeweqN","data_data_86060.md":"rfjC2dw4","data_data_92100.md":"JEHHdi4N","data_data_98010.md":"IQp134ei","data_data_71030.md":"32JZMoZj","data_data_10040.md":"EEY_H8Sr","data_data_70300.md":"vyMUi2gJ","data_data_91000.md":"r036c6j9","library_files_index_npc_index.md":"zZ04QbiU","data_data_91040.md":"3BqGnwBM","data_data_90980.md":"Ecmr0ykZ","data_data_10250.md":"qTe9LyNO","data_data_99160.md":"vGjtGb6K","data_data_90050.md":"Y-ewWVgP","data_data_93180.md":"WQXjGR04","data_data_90700.md":"lVgCWuNV","data_data_93020.md":"W5eTw9Q8","data_data_86090.md":"uZzMDRDM","data_data_90410.md":"ve1cyYu7","data_data_90360.md":"EgSwig3e","data_data_93030.md":"K4F2nTTA","data_data_90750.md":"ELfI-u53","data_data_40320.md":"ZKI6x3-V","data_data_90920.md":"AThN6pnd","data_data_86270.md":"kDZCg5Xk","data_data_60090.md":"YcsIYpER","data_data_40390.md":"0DKtGztg","data_data_91130.md":"jT-T3nVt","data_data_20150.md":"G4DgaKwu","data_data_70051.md":"dPmrREYd","data_data_30260.md":"vGCGj7bV","data_data_30430.md":"EXkq7-UO","data_data_50011.md":"2S1Cjjoc","data_data_50060.md":"IE6bembO","data_characters.md":"14QOZYx7","data_data_99371.md":"aq9g9k5i","data_data_90600.md":"Kr3rWyBu","data_data_92150.md":"O-5KqmbW","data_data_90780.md":"1IoDE2EX","data_data_90860.md":"eMC8tZMn","data_data_99050.md":"rciFrlbN","data_data_80020.md":"wCIE0Iaf","data_data_93040.md":"GLCaHBr5","data_data_90630.md":"tZ3_trGS","data_data_92280.md":"Gr8llv6s","data_data_99040.md":"sQqOpDrG","data_data_40010.md":"bzS62y64","data_data_40110.md":"w_67KPML","data_data_90160.md":"gQz_CY_I","data_data_90970.md":"eK-g9LHp","data_data_90880.md":"rtADeUT6","index.md":"AxVTR2Q6","data_data_10020.md":"Y12K3zsd","data_data_93190.md":"V8D7eRW0","data_data_30340.md":"wqMH7_Hx","data_data_93280.md":"NeDtqkva","data_data_90871.md":"3oZ_jgmO","data_data_30220.md":"NsL9Ohjg","data_data_80060.md":"ig_o4GbW","data_data_30150.md":"xf_wQgbb","data_data_92200.md":"FJOqFu2O","data_data_70010.md":"FxOhPG1a","data_data_92010.md":"U9xBzUtw","data_data_90260.md":"uVgBoHu5","data_data_92210.md":"-Y8U2k9w","data_data_10090.md":"Ygv2w8bK","data_data_60030.md":"ieKwNDvN","data_data_90840.md":"YzBw8nS0","data_data_92291.md":"---ObILx","data_data_80210.md":"5C7V7Jsi","data_data_60270.md":"_8r2d_4u","data_data_90910.md":"YmLbiXE2","data_data_90950.md":"lQ0mfwZw","data_data_60170.md":"fjQUyPKA","data_data_93100.md":"7-GKC6kG","data_data_50110.md":"m7ydHGVh","data_data_92240.md":"KrdjaDGs","data_data_92190.md":"F2Q7uK0i","data_data_60250.md":"OoFWakna","data_data_93200.md":"CWBm_I57","data_index.md":"p0KgQOph","data_data_50140.md":"nNTH9Hkt","data_data_93090.md":"9jlHvNRj","data_data_99110.md":"8QRenvHV","data_data_40140.md":"a-K8aEK_","data_data_93281.md":"btz8dtjv","library_files_index_npc.md":"XKMCnrnG","data_data_30160.md":"8JmLurkH","data_data_60120.md":"4-yAF0Lh","data_data_60080.md":"BGoQYXRD","data_data_92260.md":"GclHnkii","data_data_92292.md":"E-vps5ov","data_data_92180.md":"LU-5epTv","data_data_92270.md":"sRAca8Kf","data_data_20110.md":"vumgkKok","data_data_40190.md":"r7jxkbqZ","data_data_93050.md":"_fOE8o0s","data_data_93160.md":"QRW1SC0K","data_data_92090.md":"Byuw5_qp","data_data_93220.md":"K7woDlmf","data_data_90300.md":"PHGYbyZc","data_data_93170.md":"mMaIhDf1","data_data_20240.md":"aHyNsjKR","data_data_80120.md":"cHKphTaT","data_data_40270.md":"Z2uTnTvT","data_data_10150.md":"QWHiAH2b","data_data_50180.md":"CG3NnQ1P","data_data_90320.md":"miu-8Kng","data_data_40220.md":"B1FukItD","data_data_70321.md":"Hr64alti","data_data_91050.md":"AxtJixJS","data_data_40070.md":"ZCxoSvp_","data_data_92250.md":"lw0lVbQv","data_data_80240.md":"YKfFtb8W","data_data_70130.md":"MMW8n6Rf","data_data_90120.md":"_kWrP9jR","data_data_70340.md":"Rmj83hPZ","data_data_92290.md":"IKjcI7Bw","data_data_70180.md":"paaBZx0c","data_data_99340.md":"cx3EI6lm","use_handbook_index.md":"kBOCBPU5","data_data_90070.md":"kF2Yv36V","data_data_20090.md":"_Tyii4y_","data_data_92030.md":"rOp1FD_z","data_data_90960.md":"YtKZSzWs","data_data_50120.md":"FL9Zrrol","data_data_70080.md":"Jbx-ezV1","data_data_40200.md":"8Uu6eTUS","data_data_93140.md":"IKPc9N5w","data_data_92040.md":"5SUW6Sn0","data_data_99350.md":"vHshCj4c","data_data_70040.md":"NQ3DAbVA","data_data_60060.md":"1RINotWe","data_data_90340.md":"ineW3XtT","data_data_60280.md":"HjYw681J","data_data_90110.md":"etYdYMu-","data_data_80070.md":"qroFZvAX","data_data_10210.md":"IGJLdBdl","data_data_60100.md":"_pIfLZwC","data_data_50310.md":"UKsWV8JR","data_data_70210.md":"ug4O76-F","data_data_20180.md":"0H1HL4ZT","data_data_99150.md":"qAqUCBj9","data_data_40090.md":"0nLfxF4g","data_data_90230.md":"NF0pZwDX","data_data_93010.md":"pszPJ4gz","data_data_90280.md":"GPqrX_zh","data_data_92160.md":"zC78RXQW","data_data_80270.md":"EnWr1_DT","data_data_99130.md":"AUYQdARJ","data_data_90240.md":"WzyohTkL","library_files_index_uis.md":"E0o7pfe2","beta_1_enemies.md":"VrSxaKa7","data_data_86100.md":"r12BHv8a","library_files_index_kishins_index.md":"LYx_MWNm","data_data_86110.md":"Cu8gkbpE","data_data_40350.md":"iu83pa0V","data_data_93120.md":"-Mk0a74H","data_data_90130.md":"hz8PJjLy","data_data_50010.md":"vrchKd7h","beta_1_characters_138_salticidae.md":"QoUPci9_","data_data_86210.md":"tJJQQLBo","data_data_92060.md":"64Pslhl2","data_data_92080.md":"mwcMg0yZ","data_data_99080.md":"ZUKNQA1D","data_data_92140.md":"UCiwN6fw","data_data_70170.md":"aPe1Ouce","data_data_20120.md":"VK-hm-1W","data_data_90610.md":"USgNr4A3","data_data_71040.md":"0YTx6Cxd","data_data_80200.md":"_LkOLNHD","data_data_70160.md":"JJkvWanQ","data_data_86080.md":"eFqOa3Hx","data_data_86040.md":"uHejPRPZ","data_data_90490.md":"qI6g-nvB","data_data_80040.md":"Ycw1EEWp","data_data_90590.md":"XpI1_Keu","data_data_90730.md":"NveKOHcN","data_data_93110.md":"5bEgbOiI","data_data_93080.md":"R8RWW1JQ","data_data_80280.md":"iFlvO9f2","data_data_86120.md":"YhFlAHIb","data_data_92230.md":"mZkRCziT","data_data_70220.md":"9k5hOG0T","data_data_90640.md":"uMVWkDeJ","data_data_50040.md":"R3P-8TKd","data_data_92170.md":"L46BTuyw","data_data_90710.md":"O6mQ3DX1","data_data_90770.md":"HZ5N_XTd","library_files_index_kishins.md":"CYop_-kd","data_data_86220.md":"DgqyzRTz","data_data_80080.md":"GA_THcfP","data_data_90210.md":"LfGjfdNu","data_data_70290.md":"l5g4DpCI","data_data_90740.md":"d4aiYOXx","data_data_30100.md":"UMbokps3","data_data_93240.md":"lxEGBdDa","data_data_90140.md":"tEJhoTh3","data_data_99230.md":"4qDp39wM","data_data_90580.md":"M-8Gfjg_","data_data_90380.md":"4Og-KNiE","library_files_index_characters_index.md":"oqjolRdp","data_data_93210.md":"L69eUrr-","data_data_90400.md":"PKLu3obe","data_data_90641.md":"kAamTE56","data_data_93060.md":"41osMeDL","data_data_99120.md":"EWO9uEAc","data_data_50080.md":"mH08Uhno","data_data_20190.md":"WFcKo-yk","data_data_70060.md":"wEtEEcst","data_data_10290.md":"SBfbKS7i","data_data_60200.md":"dgRU717G","data_data_50320.md":"BLRgZ3SQ","data_data_70110.md":"bqUWMxlT","data_data_60230.md":"ZT8zCZiF","data_data_99364.md":"DxTDTdAV","library_files_index_characters_uit_index.md":"PU1qOtZZ","data_data_92120.md":"kzmqhRZi","data_data_80160.md":"qQ3VHAit","data_data_99260.md":"Oh7laOf_","data_data_30350.md":"xbySRPqK","data_data_92130.md":"TsEhFWQl","data_data_20080.md":"3WyzgbAS","data_data_70150.md":"RCpzCH92","data_data_90510.md":"O8KqAvKl","data_data_99170.md":"fttMsrvk","data_data_90781.md":"fLIIYRZY","data_data_99140.md":"-UNd25eV","data_data_90090.md":"AcltqVx1","data_data_40230.md":"NO3kiPji","use_index.md":"QO4BLaKX","data_data_92281.md":"KlLbrjn3","data_data_99060.md":"eAjSdk6C","data_data_71020.md":"MZBj-BGd","data_data_91030.md":"vaAzx-65","data_data_70190.md":"der45dJQ","data_data_90470.md":"GKBT9_aO","data_data_70230.md":"NovzOPKg","data_data_10100.md":"Bi5Nt1D5","data_data_30320.md":"CJEL3lhI","data_data_99280.md":"TafiK7fM","data_data_10190.md":"SI_a7Axc","data_data_60130.md":"jkXPDEfM","data_data_86160.md":"_bCjr7XF","data_data_50070.md":"YoFcpKjb","data_data_50020.md":"fB4hJ196","data_data_70280.md":"KzFQbm2J","data_data_90720.md":"idtqegob","data_data_60070.md":"6iKHCsdC","library_files_index_characters_uit.md":"45OMv5Ej","data_data_20100.md":"h5OAvQnY","data_data_90430.md":"03Ij2bnM","data_data_92020.md":"iPkUrrzF","data_data_60190.md":"vv6EZ2_3","data_data_70250.md":"Lb8RmlFd","data_data_90660.md":"zEQ0v7jM","library_index.md":"0E1bFS4y","data_data_70310.md":"zIS35gtc","data_data_40210.md":"Ryoa4M05","data_data_90861.md":"ougl3nos","data_data_90930.md":"A6pMT1gS","library_files_index_monster_index.md":"33e2Ro-3","data_data_90611.md":"K4oPtIkb","data_data_92220.md":"Dzhpmpop","beta_1_characters.md":"tZbuXAfr","data_data_93070.md":"RDM8V0P6","data_characters_uit.md":"zBq5zRoX","library_files_index_index.md":"UNJ57tKS","data_monster.md":"ZxgFNBC0","library_files_index_characters.md":"Hq9dVkAZ","library_files_index_index_beta.md":"k5eQHT0e"}
